qualifyzedwhutils/__init__.py
qualifyzedwhutils-0.1003.dist-info/LICENSE.txt
qualifyzedwhutils-0.1003.dist-info/METADATA
qualifyzedwhutils-0.1003.dist-info/WHEEL
qualifyzedwhutils-0.1003.dist-info/top_level.txt
qualifyzedwhutils-0.1003.dist-info/RECORD
